MANIFEST.in
README.md
setup.py
qtkanobu/__init__.py
qtkanobu/__main__.py
qtkanobu/kanobu.py
qtkanobu/main.py
qtkanobu.egg-info/PKG-INFO
qtkanobu.egg-info/SOURCES.txt
qtkanobu.egg-info/dependency_links.txt
qtkanobu.egg-info/entry_points.txt
qtkanobu.egg-info/top_level.txt
qtkanobu/mainwindow/__init__.py
qtkanobu/mainwindow/design.py
qtkanobu/mainwindow/resources_rc.py
qtkanobu/result/__init__.py
qtkanobu/result/res_.py
qtkanobu/result/resdesign.py
qtkanobu/result/resources_rc.py
qtkanobu/result/resources_res2.py