Metadata-Version: 2.1
Name: qtkanobu
Version: 0.1.0
Summary: Qt port of kanobu
Home-page: https://github.com/jDan735/qtkanobu
Author: Daniel Zakharov
Author-email: daniel734@bk.ru
License: MIT
Keywords: kanobu qt game
Platform: UNKNOWN
Classifier: Programming Language :: Python :: 3
Classifier: Programming Language :: Python :: 3.4
Classifier: Programming Language :: Python :: 3.5
Classifier: Programming Language :: Python :: 3.6
Classifier: Programming Language :: Python :: 3.7
Classifier: Programming Language :: Python :: 3.8
Classifier: License :: OSI Approved :: MIT License
Requires-Python: >=3
